sykel/__init__.py
sykel/__main__.py
sykel/package.py
sykel/version.py
sykel-0.0.12.dist-info/LICENSE
sykel-0.0.12.dist-info/METADATA
sykel-0.0.12.dist-info/WHEEL
sykel-0.0.12.dist-info/entry_points.txt
sykel-0.0.12.dist-info/top_level.txt
sykel-0.0.12.dist-info/RECORD
